mcp_cli/__init__.py
mcp_cli/__main__.py
mcp_gearbox-0.0.13.dist-info/licenses/LICENSE
mcp_gearbox-0.0.13.dist-info/METADATA
mcp_gearbox-0.0.13.dist-info/WHEEL
mcp_gearbox-0.0.13.dist-info/entry_points.txt
mcp_gearbox-0.0.13.dist-info/top_level.txt
mcp_gearbox-0.0.13.dist-info/RECORD
