Metadata-Version: 2.4
Name: mcp-gearbox
Version: 0.0.13
Summary: A command-line interface tool for MCP server management and project initialization
Author: Rohit Soni
Maintainer: Rohit Soni
License-Expression: MIT
Project-URL: Homepage, https://github.com/rohitsoni007/mcp-kit
Project-URL: Repository, https://github.com/rohitsoni007/mcp-kit
Project-URL: Issues, https://github.com/rohitsoni007/mcp-kit/issues
Project-URL: Documentation, https://github.com/rohitsoni007/mcp-kit#readme
Project-URL: Changelog, https://github.com/rohitsoni007/mcp-kit/blob/main/CHANGELOG.md
Keywords: mcp,model-context-protocol,cli,project-initialization,ai-tools
Classifier: Development Status :: 3 - Alpha
Classifier: Intended Audience :: Developers
Classifier: Operating System :: OS Independent
Classifier: Programming Language :: Python :: 3
Classifier: Programming Language :: Python :: 3.11
Classifier: Programming Language :: Python :: 3.12
Classifier: Programming Language :: Python :: 3.13
Classifier: Topic :: Software Development :: Libraries :: Python Modules
Classifier: Topic :: System :: Systems Administration
Classifier: Topic :: Utilities
Requires-Python: >=3.11
License-File: LICENSE
Requires-Dist: typer>=0.9.0
Requires-Dist: rich>=13.0.0
Requires-Dist: httpx>=0.24.0
Requires-Dist: platformdirs>=3.0.0
Requires-Dist: readchar>=4.0.0
Requires-Dist: truststore>=0.10.4
Provides-Extra: dev
Requires-Dist: pytest>=7.0.0; extra == "dev"
Requires-Dist: pytest-cov>=4.0.0; extra == "dev"
Requires-Dist: black>=22.0.0; extra == "dev"
Requires-Dist: isort>=5.10.0; extra == "dev"
Requires-Dist: flake8>=4.0.0; extra == "dev"
Requires-Dist: mypy>=0.950; extra == "dev"
Provides-Extra: test
Requires-Dist: pytest>=7.0.0; extra == "test"
Requires-Dist: pytest-cov>=4.0.0; extra == "test"
Dynamic: license-file
